literag/__init__.py
literag/__main__.py
literag/azure_retriever.py
literag/main.py
literag/openai_vectorizer.py
literag/pinecone_retriever.py
literag/retrieval_service.py
literag/text_vectorizer.py
literag-0.2.1.dist-info/METADATA
literag-0.2.1.dist-info/WHEEL
literag-0.2.1.dist-info/entry_points.txt
literag-0.2.1.dist-info/RECORD
